LICENSE
MANIFEST.in
README.md
VERSION
requirements.txt
setup.py
countergen/__init__.py
countergen/__main__.py
countergen/config.py
countergen/types.py
countergen.egg-info/PKG-INFO
countergen.egg-info/SOURCES.txt
countergen.egg-info/dependency_links.txt
countergen.egg-info/entry_points.txt
countergen.egg-info/requires.txt
countergen.egg-info/top_level.txt
countergen/augmentation/__init__.py
countergen/augmentation/data_augmentation.py
countergen/augmentation/llmd_augmenter.py
countergen/augmentation/paraphraser.py
countergen/augmentation/simple_augmenter.py
countergen/data/augdatasets/bias-from-probs.jsonl
countergen/data/augdatasets/doublebind-likable-paraphrased.jsonl
countergen/data/augdatasets/doublebind-negative-paraphrased.jsonl
countergen/data/augdatasets/doublebind-positive-paraphrased.jsonl
countergen/data/augdatasets/doublebind-unlikable-paraphrased.jsonl
countergen/data/augdatasets/doublebind.jsonl
countergen/data/augdatasets/female-stereotypes.jsonl
countergen/data/augdatasets/hate-test-muslims.jsonl
countergen/data/augdatasets/hate-test.jsonl
countergen/data/augdatasets/male-stereotypes.jsonl
countergen/data/augdatasets/simple-gender.jsonl
countergen/data/augdatasets/tiny-test.jsonl
countergen/data/augdatasets/twitter-sentiment.jsonl
countergen/data/converters/gender.json
countergen/data/converters/west_v_asia.json
countergen/data/datasets/doublebind-likable.jsonl
countergen/data/datasets/doublebind-negative-1token.jsonl
countergen/data/datasets/doublebind-negative.jsonl
countergen/data/datasets/doublebind-positive-1token.jsonl
countergen/data/datasets/doublebind-positive.jsonl
countergen/data/datasets/doublebind-unlikable.jsonl
countergen/data/datasets/female-stereotypes.jsonl
countergen/data/datasets/gender-stereotypes.jsonl
countergen/data/datasets/hate-test.jsonl
countergen/data/datasets/hate-train.jsonl
countergen/data/datasets/male-stereotypes.jsonl
countergen/data/datasets/tiny-test.jsonl
countergen/data/datasets/twitter-sentiment.jsonl
countergen/evaluation/__init__.py
countergen/evaluation/aggregators.py
countergen/evaluation/evaluation.py
countergen/evaluation/generative_models.py
countergen/tools/__init__.py
countergen/tools/api_utils.py
