Metadata-Version: 2.1
Name: countergen
Version: 1.1.0
Summary: A counterfactual dataset generator to evaluate language models.
Home-page: https://github.com/FabienRoger/Countergen
Author: SaferAI
Author-email: saferai.audit@gmail.com
Classifier: Programming Language :: Python :: 3
Classifier: Operating System :: OS Independent
Requires-Python: >=3.7
License-File: LICENSE
